getallcolumns/__init__.py
getallcolumns-0.3.dist-info/METADATA
getallcolumns-0.3.dist-info/WHEEL
getallcolumns-0.3.dist-info/top_level.txt
getallcolumns-0.3.dist-info/RECORD
