Metadata-Version: 2.1
Name: getallcolumns
Version: 0.3
Summary: getallcolumns
Author: srini
Keywords: python,pyspark,catalog,schema
Classifier: Development Status :: 1 - Planning
Classifier: Intended Audience :: Developers
Classifier: Programming Language :: Python :: 3
Classifier: Operating System :: Unix
Classifier: Operating System :: MacOS :: MacOS X
Classifier: Operating System :: Microsoft :: Windows
